README.rst
setup.cfg
setup.py
bin/dcm-api-tests
bin/dcm-assign-cloud
bin/dcm-attach-volume
bin/dcm-check-job
bin/dcm-create-account
bin/dcm-create-billing-code
bin/dcm-create-cm
bin/dcm-create-group
bin/dcm-create-machine-image
bin/dcm-create-network
bin/dcm-create-role
bin/dcm-create-server
bin/dcm-create-user
bin/dcm-create-volume
bin/dcm-delete
bin/dcm-delete-billing-code
bin/dcm-delete-group
bin/dcm-delete-network
bin/dcm-delete-volume
bin/dcm-describe-job
bin/dcm-describe-license
bin/dcm-describe-machine-image
bin/dcm-describe-server
bin/dcm-detach-volume
bin/dcm-get
bin/dcm-head
bin/dcm-list-accounts
bin/dcm-list-api-keys
bin/dcm-list-api-versions
bin/dcm-list-billing-codes
bin/dcm-list-clouds
bin/dcm-list-cm
bin/dcm-list-cm-environments
bin/dcm-list-cm-personalities
bin/dcm-list-cm-scripts
bin/dcm-list-cm-systems
bin/dcm-list-customers
bin/dcm-list-datacenters
bin/dcm-list-firewall-rules
bin/dcm-list-firewalls
bin/dcm-list-groups
bin/dcm-list-jobs
bin/dcm-list-loadbalancers
bin/dcm-list-machine-images
bin/dcm-list-networks
bin/dcm-list-rdbms
bin/dcm-list-rdbms-products
bin/dcm-list-regions
bin/dcm-list-role-assignments
bin/dcm-list-roles
bin/dcm-list-server-analytics
bin/dcm-list-server-products
bin/dcm-list-server-terminate
bin/dcm-list-servers
bin/dcm-list-snapshots
bin/dcm-list-storage-objects
bin/dcm-list-subscriptions
bin/dcm-list-users
bin/dcm-list-volumes
bin/dcm-pause-server
bin/dcm-post
bin/dcm-put
bin/dcm-rename-server
bin/dcm-set-acl
bin/dcm-set-role
bin/dcm-set-server-terminate
bin/dcm-start-server
bin/dcm-stop-server
bin/dcm-terminate-server
bin/dcm-update-group
bin/dcm-update-machine-image-billing-code
bin/dcm-update-machine-image-group
bin/dcm-update-server-billing-code
bin/dcm-update-server-group
bin/dcm-update-volume-billing-code
bin/dcm-update-volume-group
bin/mixcoatl
mixcoatl/__init__.py
mixcoatl/auth.py
mixcoatl/resource.py
mixcoatl/resource_utils.py
mixcoatl/utils.py
mixcoatl.egg-info/PKG-INFO
mixcoatl.egg-info/SOURCES.txt
mixcoatl.egg-info/dependency_links.txt
mixcoatl.egg-info/not-zip-safe
mixcoatl.egg-info/pbr.json
mixcoatl.egg-info/requires.txt
mixcoatl.egg-info/top_level.txt
mixcoatl/admin/__init__.py
mixcoatl/admin/account.py
