Metadata-Version: 1.1
Name: mixcoatl
Version: 1.5.0
Summary: Dell Cloud Manager API Python wrapper
Home-page: https://github.com/enStratus/mixcoatl
Author: Dell Cloud Management Team
Author-email: mixcoatl@enstratius.com
License: Apache 2.0
Platform: UNKNOWN
Classifier: Development Status :: 4 - Beta
Classifier: Natural Language :: English
Classifier: License :: OSI Approved :: Apache Software License
Classifier: Programming Language :: Python
Classifier: Programming Language :: Python :: 2.6
Classifier: Programming Language :: Python :: 2.7
